{
  "SchemaVersion": 1,
  "TemplateId": "Games/Blank",
  "Name": "PB_Template_Games_Blank_Name",
  "DisplayName": "PB_Template_Games_Blank_Name",
  "Description": "PB_Template_Games_Blank_Description",
  "Icon": "Media/Icon.png",
  "Preview": "Media/Preview.png",
  "SourceFolder": ".",
  "Category": "C44E7604-B265-40D8-9442-11A01ECE334C",
  "AuthoringMounts": [
    {
      "Name": "Content",
      "RelativePath": "Content"
    }
  ],
  "LocalFolderMounts": [],
  "StarterScene": {
    "AssetUri": "asset:///Content/Scenes/Main.oscene.json",
    "RelativePath": "Content/Scenes/Main.oscene.json",
    "OpenOnCreate": true
  },
  "StarterContent": [
    {
      "AssetUri": "asset:///Content/Materials/Default.omat.json",
      "RelativePath": "Content/Materials/Default.omat.json",
      "Kind": "Material"
    }
  ],
  "PreviewImages": [
    "Media/Preview.png"
  ]
}
